akilia/__init__.py
akilia/add.py
akilia/main.py
akilia-0.2.1.dist-info/licenses/LICENSE
akilia-0.2.1.dist-info/METADATA
akilia-0.2.1.dist-info/WHEEL
akilia-0.2.1.dist-info/top_level.txt
akilia-0.2.1.dist-info/RECORD
