Metadata-Version: 2.4
Name: akilia
Version: 0.2.1
Summary: AI systems and low-field MRI tools for Africa
Author: Leo Kinyera
Author-email: leo@example.com
Requires-Python: >=3.8
License-File: LICENSE
Requires-Dist: matplotlib
Dynamic: author
Dynamic: author-email
Dynamic: license-file
Dynamic: requires-dist
Dynamic: requires-python
Dynamic: summary
